{
  "schemaVersion": 1,
  "id": "xp_utilities",
  "version": "${version}",

  "name": "XP Utilities",
  "description": "This is an example description! Tell everyone what your mod is about!",
  "authors": [
    "jhbuchanan45"
  ],
  "contact": {
    "homepage": "https://github.com/jhbuchanan45/xp-utilities",
    "sources": "https://github.com/jhbuchanan45/xp-utilities"
  },

  "license": "MIT",
  "icon": "assets/xp_utilities/icon.png",

  "environment": "*",
  "entrypoints": {
    "main": [
      "dev.maniac.xpUtilities.XPUtilities"
    ],
    "client": [
      "dev.maniac.xpUtilities.XPUtilitiesClient"
    ]
  },
  "mixins": [
    "xp_utilities.mixins.json"
  ],

  "depends": {
    "fabricloader": ">=0.11.3",
    "fabric": "*",
    "minecraft": "1.17.x",
    "java": ">=16"
  },
  "suggests": {
    "another-mod": "*"
  }
}
